LICENSE
README.md
setup.cfg
setup.py
nylas_legacy/__init__.py
nylas_legacy/_client_sdk_version.py
nylas_legacy/config.py
nylas_legacy/utils.py
nylas_legacy.egg-info/PKG-INFO
nylas_legacy.egg-info/SOURCES.txt
nylas_legacy.egg-info/dependency_links.txt
nylas_legacy.egg-info/requires.txt
nylas_legacy.egg-info/top_level.txt
nylas_legacy/client/__init__.py
nylas_legacy/client/authentication_models.py
nylas_legacy/client/client.py
nylas_legacy/client/delta_collection.py
nylas_legacy/client/delta_models.py
nylas_legacy/client/errors.py
nylas_legacy/client/neural_api_models.py
nylas_legacy/client/outbox_models.py
nylas_legacy/client/restful_model_collection.py
nylas_legacy/client/restful_models.py
nylas_legacy/client/scheduler_models.py
nylas_legacy/client/scheduler_restful_model_collection.py
nylas_legacy/services/__init__.py
nylas_legacy/services/tunnel.py
tests/__init__.py
tests/conftest.py
tests/test_accounts.py
tests/test_authentication.py
tests/test_client.py
tests/test_components.py
tests/test_contacts.py
tests/test_delta.py
tests/test_drafts.py
tests/test_events.py
tests/test_files.py
tests/test_filter.py
tests/test_folders.py
tests/test_job_status.py
tests/test_labels.py
tests/test_messages.py
tests/test_neural.py
tests/test_outbox.py
tests/test_resources.py
tests/test_scheduler.py
tests/test_search.py
tests/test_send_error_handling.py
tests/test_threads.py
tests/test_tunnel.py
tests/test_webhooks.py