Metadata-Version: 2.1
Name: nylas-legacy
Version: 5.15.0
Summary: Python bindings for the Nylas API v2 (legacy).
Home-page: https://github.com/nylas/nylas-python-legacy
Author: Nylas Team
Author-email: support@nylas.com
License: MIT
Keywords: inbox app appserver email nylas contacts calendar
License-File: LICENSE
Requires-Dist: requests[security]>=2.4.2
Requires-Dist: six>=1.4.1
Requires-Dist: urlobject
Requires-Dist: enum34>=1.1.10; python_version <= "3.4"
Requires-Dist: websocket-client==0.59.0
Provides-Extra: test
Requires-Dist: pytest; extra == "test"
Requires-Dist: pytest-cov; extra == "test"
Requires-Dist: pytest-timeout; extra == "test"
Requires-Dist: pytest-mock; extra == "test"
Requires-Dist: responses==0.10.5; extra == "test"
Requires-Dist: twine; extra == "test"
Requires-Dist: pytz; extra == "test"
Requires-Dist: mock; python_version < "3.3" and extra == "test"
Provides-Extra: release
Requires-Dist: bumpversion>=0.5.0; extra == "release"
Requires-Dist: twine>=3.4.2; extra == "release"
